wirio/__init__.py
wirio/_integrations/__init__.py
wirio/_integrations/_fastapi_dependency_injection.py
wirio/_service_lookup/__init__.py
wirio/_service_lookup/_async_concurrent_dictionary.py
wirio/_service_lookup/_async_factory_call_site.py
wirio/_service_lookup/_asyncio_reentrant_lock.py
wirio/_service_lookup/_call_site_chain.py
wirio/_service_lookup/_call_site_factory.py
wirio/_service_lookup/_call_site_kind.py
wirio/_service_lookup/_call_site_runtime_resolver.py
wirio/_service_lookup/_call_site_visitor.py
wirio/_service_lookup/_constant_call_site.py
wirio/_service_lookup/_constructor_call_site.py
wirio/_service_lookup/_constructor_information.py
wirio/_service_lookup/_parameter_information.py
wirio/_service_lookup/_result_cache.py
wirio/_service_lookup/_runtime_service_provider_engine.py
wirio/_service_lookup/_service_call_site.py
wirio/_service_lookup/_service_identifier.py
wirio/_service_lookup/_service_provider_call_site.py
wirio/_service_lookup/_service_provider_engine.py
wirio/_service_lookup/_supports_async_context_manager.py
wirio/_service_lookup/_supports_context_manager.py
wirio/_service_lookup/_sync_factory_call_site.py
wirio/_service_lookup/_typed_type.py
wirio/_service_lookup/call_site_result_cache_location.py
wirio/_service_lookup/service_cache_key.py
wirio/_utils/__init__.py
wirio/_utils/_param_utils.py
wirio/abstractions/__init__.py
wirio/abstractions/base_service_provider.py
wirio/abstractions/keyed_service.py
wirio/abstractions/keyed_service_provider.py
wirio/abstractions/service_key_lookup_mode.py
wirio/abstractions/service_provider_is_keyed_service.py
wirio/abstractions/service_provider_is_service.py
wirio/abstractions/service_scope.py
wirio/abstractions/service_scope_factory.py
wirio/annotations.py
wirio/exceptions.py
wirio/py.typed
wirio/service_collection.py
wirio/service_descriptor.py
wirio/service_lifetime.py
wirio/service_provider.py
wirio/service_provider_engine_scope.py
wirio/wirio_undefined.py
wirio-0.8.0.dist-info/licenses/LICENSE
wirio-0.8.0.dist-info/WHEEL
wirio-0.8.0.dist-info/METADATA
wirio-0.8.0.dist-info/RECORD
