Metadata-Version: 2.4
Name: wirio
Version: 0.8.0
Summary: Powerful Dependency Injection with Python
Keywords: dependency injection,di,inversion of control,ioc,fastapi
Author: Andreu Codina
License-Expression: MIT
License-File: LICENSE
Classifier: Development Status :: 5 - Production/Stable
Classifier: Programming Language :: Python :: 3.14
Classifier: Programming Language :: Python :: 3.13
Classifier: Intended Audience :: Developers
Requires-Dist: fastapi[standard-no-fastapi-cloud-cli]>=0.118.0
Requires-Python: >=3.13
Project-URL: Homepage, https://github.com/AndreuCodina/wirio
Project-URL: Repository, https://github.com/AndreuCodina/wirio
Project-URL: Documentation, https://github.com/AndreuCodina/wirio
Project-URL: Changelog, https://github.com/AndreuCodina/wirio/releases
